{
  "placeholderImages": [
    {
      "id": "hero-banner",
      "description": "A cinematic shot of a luxury villa at dusk.",
      "imageUrl": "https://picsum.photos/seed/hero/1920/1080",
      "imageHint": "luxury villa"
    },
    {
      "id": "prop-1",
      "description": "Interior of a modern apartment with city views.",
      "imageUrl": "https://picsum.photos/seed/p1/600/400",
      "imageHint": "modern apartment"
    },
    {
      "id": "prop-2",
      "description": "A stunning beachfront villa with a pool.",
      "imageUrl": "https://picsum.photos/seed/p2/600/400",
      "imageHint": "beachfront house"
    },
    {
      "id": "prop-3",
      "description": "A luxurious city penthouse with panoramic views at night.",
      "imageUrl": "https://picsum.photos/seed/p3/600/400",
      "imageHint": "city penthouse"
    },
    {
      "id": "prop-4",
      "description": "A sprawling country estate with large gardens.",
      "imageUrl": "https://picsum.photos/seed/p4/600/400",
      "imageHint": "country estate"
    },
    {
      "id": "prop-5",
      "description": "A beautiful family home in a quiet suburban neighborhood.",
      "imageUrl": "https://picsum.photos/seed/p5/600/400",
      "imageHint": "suburban home"
    },
    {
      "id": "prop-6",
      "description": "A cozy and modern mountain cabin in the woods.",
      "imageUrl": "https://picsum.photos/seed/p6/600/400",
      "imageHint": "mountain cabin"
    },
    {
        "id": "testimonial-1",
        "description": "A professional portrait of a man in a business suit.",
        "imageUrl": "https://picsum.photos/seed/t1/100/100",
        "imageHint": "professional man"
    },
    {
        "id": "testimonial-2",
        "description": "A professional portrait of a woman in an office setting.",
        "imageUrl": "https://picsum.photos/seed/t2/100/100",
        "imageHint": "professional woman"
    },
    {
        "id": "testimonial-3",
        "description": "A modern, abstract logo for a development company.",
        "imageUrl": "https://picsum.photos/seed/t3/100/100",
        "imageHint": "company logo"
    },
    {
        "id": "testimonial-4",
        "description": "A portrait of a man with a blurred background of a city.",
        "imageUrl": "https://picsum.photos/seed/t4/100/100",
        "imageHint": "man city"
    }
  ]
}
